mcp_server_akshare/__init__.py
mcp_server_akshare/api.py
mcp_server_akshare/server.py
akshare_mcp_server-0.1.1.dist-info/METADATA
akshare_mcp_server-0.1.1.dist-info/WHEEL
akshare_mcp_server-0.1.1.dist-info/entry_points.txt
akshare_mcp_server-0.1.1.dist-info/top_level.txt
akshare_mcp_server-0.1.1.dist-info/RECORD
