Metadata-Version: 2.4
Name: akshare-mcp-server
Version: 0.1.1
Summary: MCP server for AKShare financial data
Author-email: Your Name <your.email@example.com>
License: MIT
Requires-Python: >=3.13
Requires-Dist: akshare>=1.16.67
Requires-Dist: asyncio>=3.4.3
Requires-Dist: black>=25.1.0
Requires-Dist: httpx>=0.28.1
Requires-Dist: isort>=6.0.1
Requires-Dist: mcp>=1.6.0
Requires-Dist: mypy>=1.15.0
Requires-Dist: numpy>=2.2.4
Requires-Dist: pandas>=2.2.3
Requires-Dist: pytest-asyncio>=0.26.0
Requires-Dist: python-dotenv>=1.1.0
